[
  {
    "id": 1,
    "img": "/images/slides/questions-slide-1@2x.webp",
    "alt": "Дівчина стоїть спиною, поклавши руку на своє плече",
    "label": "Самооцінка"
  },
  {
    "id": 2,
    "img": "/images/slides/questions-slide-2@2x.webp",
    "alt": "Пара чоловіка і жінки обіймаються",
    "label": "Відносини"
  },
  {
    "id": 3,
    "img": "/images/slides/questions-slide-3@2x.webp",
    "alt": "Брюнетка в коричневій майці направила лице до сонячних променів",
    "label": "Жіночність"
  },
  {
    "id": 4,
    "img": "/images/slides/questions-slide-4@2x.webp",
    "alt": "Брюнетка в коричневому світері на білому фоні",
    "label": "Розвиток чуттєвості"
  },
  {
    "id": 5,
    "img": "/images/slides/questions-slide-5@2x.webp",
    "alt": "Дівчина сидить за столом і малює",
    "label": "Розвиток творчого потенціалу"
  },
  {
    "id": 6,
    "img": "/images/slides/questions-slide-6@2x.webp",
    "alt": "Дівчина сидить в позі лотоса і медитує",
    "label": "Релакс та ін."
  }
]
